[
    {
        "name": "Advana Gamechanger",
        "url": "https://gamechanger.advana.data.mil/#/gamechanger",
        "desc": "search over 50,000 DoD policy documents",
        "category": "General",
        "branch": "DoD",
        "featured": false,
        "cac": false
    },
    {
        "name": "CitiManager",
        "url": "https://home.cards.citidirect.com/CommercialCard/login",
        "desc": "official site for CitiManager DoD GTC cards, providing resources for managing Citi accounts and services",
        "category": "Financial",
        "branch": "DoD",
        "featured": false,
        "cac": false
    },
    {
        "name": "DAF E-Learning",
        "url": "https://usaf.percipio.com/login?state=%2F#/",
        "desc": "official site for DAF E-Learning, providing online training and education resources",
        "category": "Education",
        "branch": "U.S. Air Force",
        "featured": false,
        "cac": false
    },
    {
        "name": "Defense Acquisition University (DAU)",
        "url": "https://www.dau.edu",
        "desc": "official site for DAU, providing training and resources for defense acquisition professionals",
        "category": "Education",
        "branch": "DoD",
        "featured": false,
        "cac": true
    },
    {
        "name": "Defense Finance Accounting Service (DFAS)",
        "url": "https://www.dfas.mil/",
        "desc": "official site for military pay information, including pay tables and entitlements",
        "category": "Financial",
        "branch": "DoD",
        "featured": false,
        "cac": false
    },
    {
        "name": "Defense Personal Property System (DPPS)",
        "url": "https://dps.move.mil/cust/standard/user/home.xhtml",
        "desc": "official site for military personal property relocation information, including moving allowances and benefits",
        "category": "PCS/Moving",
        "branch": "DoD",
        "featured": false,
        "cac": false
    },
    {
        "name": "Defense Travel Management Office (DTMO)",
        "url": "https://www.defensetravel.dod.mil/",
        "desc": "official site for military travel information, including travel allowances and benefits",
        "category": "PCS/Moving",
        "branch": "DoD",
        "featured": false,
        "cac": false
    },
    {
        "name": "Defense Travel System (DTS)",
        "url": "https://www.defensetravel.dod.mil/",
        "desc": "official site for the Defense Travel System, providing information on travel policies and procedures",
        "category": "Travel",
        "branch": "DoD",
        "featured": false,
        "cac": false
    },
    {
        "name": "Digital University",
        "url": "https://digitalu.af.mil/app",
        "desc": "official site for Digital University, providing online training and education resources for Air Force members",
        "category": "Education",
        "branch": "DoD",
        "featured": false,
        "cac": false
    },
    {
        "name": "DoD SAFE",
        "url": "https://safe.apps.mil/",
        "desc": "official site for the DoD Secure Access File Exchange, providing a secure way to share files",
        "category": "General",
        "branch": "DoD",
        "featured": false,
        "cac": false
    },
    {
        "name": "DOTS Web Transfer Portal",
        "url": "https://dots.dodiis.mil/webtransfer/#/",
        "desc": "official site for securely transferring files to higher classification domains (NIPR -> SIPR)",
        "category": "General",
        "branch": "DoD",
        "featured": false,
        "cac": false
    },
    {
        "name": "Executive Services Directory (ESD)",
        "url": "https://www.esd.whs.mil/",
        "desc": "official site for the Executive Services Directorate",
        "category": "General",
        "branch": "DoD",
        "featured": false,
        "cac": false
    },
    {
        "name": "GigEagle",
        "url": "https://gigeagle.mil/",
        "desc": "official site for the GigEagle program, providing resources for military families",
        "category": "General",
        "branch": "DoD",
        "featured": false,
        "cac": false
    },
    {
        "name": "H&R Block Military Tax Services",
        "url": "https://www.hrblock.com/tax-center/lifestyle/military/",
        "desc": "official site for H&R Block's military tax services, providing resources and support for military members",
        "category": "Financial",
        "branch": "DoD",
        "featured": false,
        "cac": false
    },
    {
        "name": "Health.mil Psychological Health Resource Center",
        "url": "https://www.health.mil/Military-Health-Topics/Centers-of-Excellence/Psychological-Health-Center-of-Excellence/Psychological-Health-Resource-Center",
        "desc": "official site for military mental health and psychological health information",
        "category": "Health",
        "branch": "DoD",
        "featured": true,
        "cac": false
    },
    {
        "name": "Homes.mil",
        "url": "https://www.homes.mil/",
        "desc": "official site for military housing information, including resources for finding and securing housing",
        "category": "PCS/Moving",
        "branch": "DoD",
        "featured": false,
        "cac": false
    },
    {
        "name": "Human Performance Resources",
        "url": "https://www.hprc-online.org/",
        "desc": "official site for Human Performance Resources, providing a wide range of resources for military members",
        "category": "Health",
        "branch": "DoD",
        "featured": false,
        "cac": false
    },
    {
        "name": "ID Card Office Online",
        "url": "https://idco.dmdc.osd.mil/idco/",
        "desc": "official site for the ID Card Office, providing information on ID cards and related services",
        "category": "General",
        "branch": "DoD",
        "featured": false,
        "cac": false
    },
    {
        "name": "Intelink",
        "url": "https://www.intelink.gov/",
        "desc": "official site for the Intelink collaboration platform",
        "category": "General",
        "branch": "DoD",
        "featured": false,
        "cac": false
    },
    {
        "name": "IRS Military Site",
        "url": "https://www.irs.gov/individuals/military",
        "desc": "official IRS site for military tax information, including deductions and credits",
        "category": "Financial",
        "branch": "DoD",
        "featured": false,
        "cac": false
    },
    {
        "name": "Joint Knowledge Online (JKO)",
        "url": "https://www.jcs.mil/JKO/",
        "desc": "official site for training and educational resources for the joint force",
        "category": "Education",
        "branch": "DoD",
        "featured": false,
        "cac": false
    },
    {
        "name": "LeaveWeb",
        "url": "https://leave.af.mil/profile/%23%7BtabId%7D",
        "desc": "official site for managing leave requests and balances",
        "category": "General",
        "branch": "DoD",
        "featured": false,
        "cac": false
    },
    {
        "name": "Military Money Manual",
        "url": "https://militarymoneymanual.com/",
        "desc": "provides independent financial education and resources for military members and their families",
        "category": "Financial",
        "branch": "Non-DoD",
        "featured": true,
        "cac": false
    },
    {
        "name": "Military OneSource",
        "url": "https://www.militaryonesource.mil/",
        "desc": "official site for military members and families, providing a wide range of resources and support services",
        "category": "General",
        "branch": "DoD",
        "featured": false,
        "cac": false
    },
    {
        "name": "Military.com",
        "url": "https://www.military.com/",
        "desc": "provides news, benefits information, and resources for military members and their families",
        "category": "General",
        "branch": "Non-DoD",
        "featured": false,
        "cac": false
    },
    {
        "name": "MilitaryPay",
        "url": "https://militarypay.defense.gov/",
        "desc": "official site for military pay information, including basic pay, allowances, and benefits",
        "category": "Financial",
        "branch": "DoD",
        "featured": false,
        "cac": false
    },
    {
        "name": "milConnect",
        "url": "https://milconnect.dmdc.osd.mil/milconnect/",
        "desc": "official site for military members and families to access benefits and services",
        "category": "General",
        "branch": "DoD",
        "featured": false,
        "cac": false
    },
    {
        "name": "MHS Genesis",
        "url": "https://my.mhsgenesis.health.mil/pages/home",
        "desc": "official site for MHS Genesis, providing a wide range of health care resources for military members",
        "category": "Health",
        "branch": "DoD",
        "featured": false,
        "cac": false
    },
    {
        "name": "MyPay",
        "url": "https://mypay.dfas.mil/#/",
        "desc": "official online pay management system for military members, retirees, and their families",
        "category": "Financial",
        "branch": "DoD",
        "featured": false,
        "cac": false
    },
    {
        "name": "NIPRGPT",
        "url": "https://niprgpt.mil/storefront",
        "desc": "official site for the DoD AI chat platform",
        "category": "General",
        "branch": "DoD",
        "featured": false,
        "cac": false
    },
    {
        "name": "O'Reilly Textbooks",
        "url": "https://www.oreilly.com/",
        "desc": "official site for O'Reilly Media, providing a wide range of textbooks and online resources for military members",
        "category": "Education",
        "branch": "Non-DoD",
        "featured": false,
        "cac": false
    },
    {
        "name": "OPM - Military Leave",
        "url": "https://www.opm.gov/policy-data-oversight/pay-leave/pay-administration/fact-sheets/military-leave/",
        "desc": "official Office of Personnel Management site for military leave policies and information",
        "category": "General",
        "branch": "DoD",
        "featured": false,
        "cac": false
    },
    {
        "name": "Outlook Webmail",
        "url": "https://webmail.apps.mil/mail/",
        "desc": "official site for Outlook Webmail, providing access to military email accounts",
        "category": "General",
        "branch": "DoD",
        "featured": false,
        "cac": false
    },
    {
        "name": "SGLI",
        "url": "https://www.va.gov/life-insurance/options-eligibility/sgli/",
        "desc": "official site for Servicemembers' Group Life Insurance, providing information on coverage and benefits",
        "category": "General",
        "branch": "DoD",
        "featured": false,
        "cac": false
    },
    {
        "name": "The Military Wallet",
        "url": "https://themilitarywallet.com/",
        "desc": "provides independent financial resources and tools for military members and their families",
        "category": "Financial",
        "branch": "Non-DoD",
        "featured": false,
        "cac": false
    },
    {
        "name": "Thrift Savings Plan (TSP)",
        "url": "https://www.tsp.gov/",
        "desc": "official site for the Thrift Savings Plan, a retirement savings plan for members of the uniformed services",
        "category": "Financial",
        "branch": "DoD",
        "featured": false,
        "cac": false
    },
    {
        "name": "Transition Assistance Program (TAP)",
        "url": "https://www.dodtap.mil/dodtap/app/home",
        "desc": "official site for the Transition Assistance Program, providing resources for transitioning service members",
        "category": "General",
        "branch": "DoD",
        "featured": false,
        "cac": false
    },
    {
        "name": "TRICARE",
        "url": "https://www.tricare.mil/",
        "desc": "official site for TRICARE, providing health care resources for military members",
        "category": "Health",
        "branch": "DoD",
        "featured": false,
        "cac": false
    },
    {
        "name": "U.S. Armed Forces Legal Assistance",
        "url": "https://legalassistance.law.af.mil/",
        "desc": "official site for the U.S. Armed Forces Legal Assistance, providing legal resources for service members",
        "category": "Legal",
        "branch": "DoD",
        "featured": false,
        "cac": false
    },
    {
        "name": "VA Education Benefits",
        "url": "https://www.va.gov/education/",
        "desc": "official site for military education information, including GI Bill benefits and resources",
        "category": "Education",
        "branch": "Non-DoD",
        "featured": false,
        "cac": false
    }
]